asciiarttools/__init__.py
asciiarttools/__main__.py
asciiarttools/asciiarttools.py
asciiarttools-0.0.3.dist-info/LICENSE
asciiarttools-0.0.3.dist-info/METADATA
asciiarttools-0.0.3.dist-info/WHEEL
asciiarttools-0.0.3.dist-info/entry_points.txt
asciiarttools-0.0.3.dist-info/top_level.txt
asciiarttools-0.0.3.dist-info/RECORD
