Metadata-Version: 2.1
Name: asciiarttools
Version: 0.0.3
Summary: A package that converts image to ASCII art, developed with pyenv, built with build using setuptools, uploaded to PyPI using twine, and distributed via pip.
Author-email: Wenni Fan <wf630@nyu.edu>, David Adler <dga268@nyu.edu>, Jiawei Zhang <jiawei.zhang@nyu.edu>, Michael Ma <michael.ma@nyu.edu>
License: GNU GENERAL PUBLIC LICENSE
Project-URL: Homepage, https://github.com/software-students-fall2022/python-package-exercise-project-3-team-8
Project-URL: Repository, https://github.com/software-students-fall2022/python-package-exercise-project-3-team-8.git
Project-URL: Bug Tracker, https://github.com/software-students-fall2022/python-package-exercise-project-3-team-8/issues
Keywords: python,package,build,tutorial
Classifier: Programming Language :: Python :: 3
Classifier: Intended Audience :: Education
Classifier: License :: OSI Approved :: GNU General Public License v3 (GPLv3)
Classifier: Operating System :: OS Independent
Requires-Python: >=3.7
License-File: LICENSE
Requires-Dist: numpy (>=1.21.5)
Requires-Dist: Pillow (>=9.0.1)
Provides-Extra: dev
Requires-Dist: pytest ; extra == 'dev'
